janginfo_organizer/__init__.py
janginfo_organizer/main.py
janginfo_organizer/tig_rename.py
janginfo_organizer-1.1.2.data/scripts/janginfo_organizer
janginfo_organizer-1.1.2.data/scripts/tig_rename
janginfo_organizer-1.1.2.dist-info/LICENSE
janginfo_organizer-1.1.2.dist-info/METADATA
janginfo_organizer-1.1.2.dist-info/WHEEL
janginfo_organizer-1.1.2.dist-info/top_level.txt
janginfo_organizer-1.1.2.dist-info/RECORD
