Metadata-Version: 2.1
Name: janginfo-organizer
Version: 1.1.2
Summary: Package for distribution
Home-page: https://github.com/MSjeon27/janginfo_organizer
Author: msjeon27
Author-email: msjeon27@cau.ac.kr
License: UNKNOWN
Download-URL: https://github.com/MSjeon27/janginfo_organizer
Keywords: JANGINFOORGANIZER,janginfoorganizer
Platform: UNKNOWN
Classifier: Programming Language :: Python :: 3.6
Classifier: License :: OSI Approved :: MIT License
Classifier: Operating System :: OS Independent
Requires-Python: >=3.6
Requires-Dist: argparse
Requires-Dist: Bio
